MANIFEST.in
README.rst
setup.py
tgext/__init__.py
tgext.routes.egg-info/PKG-INFO
tgext.routes.egg-info/SOURCES.txt
tgext.routes.egg-info/dependency_links.txt
tgext.routes.egg-info/entry_points.txt
tgext.routes.egg-info/namespace_packages.txt
tgext.routes.egg-info/not-zip-safe
tgext.routes.egg-info/requires.txt
tgext.routes.egg-info/top_level.txt
tgext/routes/__init__.py
tgext/routes/decorators.py
tgext/routes/dispatch.py