Metadata-Version: 1.1
Name: tgext.routes
Version: 0.2.0
Summary: Routes based dispatching for TurboGears2
Home-page: https://github.com/TurboGears/tgext.routes
Author: Alessandro Molina
Author-email: alessandro.molina@axant.it
License: MIT
Keywords: turbogears2.extension
Platform: UNKNOWN
Classifier: Environment :: Web Environment
Classifier: Topic :: Software Development :: Libraries :: Python Modules
Classifier: Framework :: TurboGears
